README.md
setup.py
activecampaign3/__init__.py
activecampaign3/config.py
activecampaign3/contact.py
activecampaign3/deal.py
activecampaign3/ecommerce_connection.py
activecampaign3/group.py
activecampaign3/logger.py
activecampaign3/mailing_list.py
activecampaign3/pipeline.py
activecampaign3/resource.py
activecampaign3/stage.py
activecampaign3/task.py
activecampaign3/user.py
activecampaign3.egg-info/PKG-INFO
activecampaign3.egg-info/SOURCES.txt
activecampaign3.egg-info/dependency_links.txt
activecampaign3.egg-info/requires.txt
activecampaign3.egg-info/top_level.txt