Metadata-Version: 1.1
Name: activecampaign3
Version: 0.0.3.1
Summary: ActiveCampaign v3 API Wrapper
Home-page: https://github.com/batsimprov/activecampaign3
Author: Ana Nelson
Author-email: ana@ananelson.com
License: UNKNOWN
Platform: UNKNOWN
Classifier: Development Status :: 3 - Alpha
Classifier: Environment :: Console
Classifier: Intended Audience :: Developers
Classifier: License :: OSI Approved :: BSD License
Classifier: Topic :: Office/Business :: Groupware
